ocrd_fork_ocropy-1.4.0a4.data/scripts/ocropus-dewarp
ocrd_fork_ocropy-1.4.0a4.data/scripts/ocropus-econf
ocrd_fork_ocropy-1.4.0a4.data/scripts/ocropus-errs
ocrd_fork_ocropy-1.4.0a4.data/scripts/ocropus-gpageseg
ocrd_fork_ocropy-1.4.0a4.data/scripts/ocropus-gtedit
ocrd_fork_ocropy-1.4.0a4.data/scripts/ocropus-hocr
ocrd_fork_ocropy-1.4.0a4.data/scripts/ocropus-linegen
ocrd_fork_ocropy-1.4.0a4.data/scripts/ocropus-lpred
ocrd_fork_ocropy-1.4.0a4.data/scripts/ocropus-ltrain
ocrd_fork_ocropy-1.4.0a4.data/scripts/ocropus-nlbin
ocrd_fork_ocropy-1.4.0a4.data/scripts/ocropus-rpred
ocrd_fork_ocropy-1.4.0a4.data/scripts/ocropus-rtrain
ocrd_fork_ocropy-1.4.0a4.data/scripts/ocropus-visualize-results
ocrolib/__init__.py
ocrolib/chars.py
ocrolib/common.py
ocrolib/defaults.py
ocrolib/edist.py
ocrolib/exceptions.py
ocrolib/hocr.py
ocrolib/lang.py
ocrolib/ligatures.py
ocrolib/lineest.py
ocrolib/lstm.py
ocrolib/morph.py
ocrolib/psegutils.py
ocrolib/sl.py
ocrolib/toplevel.py
ocrolib/utils.py
ocrd_fork_ocropy-1.4.0a4.dist-info/LICENSE
ocrd_fork_ocropy-1.4.0a4.dist-info/METADATA
ocrd_fork_ocropy-1.4.0a4.dist-info/WHEEL
ocrd_fork_ocropy-1.4.0a4.dist-info/top_level.txt
ocrd_fork_ocropy-1.4.0a4.dist-info/RECORD
