Metadata-Version: 2.1
Name: ocrd-fork-ocropy
Version: 1.4.0a4
Summary: The OCRopy RNN-based Text Line Recognizer
Home-page: https://github.com/tmbdev/ocropy
Author: Thomas Breuel
Maintainer: Konstantin Baierer
Maintainer-email: unixprog@gmail.com
License: Apache-2.0
Keywords: OCR,optical character recognition,ocropy,ocropus,kraken,calamari
Platform: UNKNOWN
Requires-Python: >=2.7
License-File: LICENSE
Requires-Dist: numpy (>=1.15.4)
Requires-Dist: scipy (>=1.1.0)
Requires-Dist: matplotlib (>=2.2.3)
Requires-Dist: imageio (>=2.4.1)
Requires-Dist: Pillow (>=2.7.0)
Requires-Dist: lxml (>=3.5.0)
Requires-Dist: six (>=1.11.0)
